mcpscanner/__init__.py
mcpscanner/__main__.py
crowdstrike_aidr_mcpscanner-0.1.0.dist-info/WHEEL
crowdstrike_aidr_mcpscanner-0.1.0.dist-info/entry_points.txt
crowdstrike_aidr_mcpscanner-0.1.0.dist-info/METADATA
crowdstrike_aidr_mcpscanner-0.1.0.dist-info/RECORD
