Metadata-Version: 2.4
Name: crowdstrike-aidr-mcpscanner
Version: 0.1.0
Summary: A command-line tool for analyzing MCP servers.
Author: CrowdStrike
Author-email: CrowdStrike <support@crowdstrike.com>
License-Expression: MIT
Requires-Dist: crowdstrike-aidr~=0.4.0
Requires-Dist: cyclopts~=4.3.0
Requires-Dist: fastembed~=0.7.4
Requires-Dist: fastmcp~=2.13.3
Requires-Dist: mcp~=1.22.0
Requires-Dist: pydantic~=2.12.5
Requires-Dist: pyjson5~=2.0.0
Requires-Dist: rich~=14.2.0
Requires-Dist: scipy~=1.16.3
Requires-Python: >=3.12
